tend_odoo-0.0.0-py3.5-nspkg.pth
bobtemplates/odoo/__init__.py
bobtemplates/odoo/hooks.py
tend_odoo-0.0.0.dist-info/DESCRIPTION.rst
tend_odoo-0.0.0.dist-info/METADATA
tend_odoo-0.0.0.dist-info/RECORD
tend_odoo-0.0.0.dist-info/WHEEL
tend_odoo-0.0.0.dist-info/metadata.json
tend_odoo-0.0.0.dist-info/namespace_packages.txt
tend_odoo-0.0.0.dist-info/top_level.txt
