Metadata-Version: 2.0
Name: tend-odoo
Version: 0.0.0
Summary: mr.bob templates for Odoo projects
Home-page: http://github.com/acsone/bobtemplates.odoo
Author: ACSONE SA/NV
Author-email: info@acsone.eu
License: LGPLv3
Platform: UNKNOWN
Classifier: Development Status :: 5 - Production/Stable
Classifier: Intended Audience :: Developers
Classifier: License :: OSI Approved :: GNU Affero General Public License v3 or later (AGPLv3+)
Classifier: Operating System :: OS Independent
Classifier: Programming Language :: Python
Classifier: Framework :: Odoo
Requires-Dist: mr.bob
